pdf_merger.py
pdf_merger_advanced-2.0.0.dist-info/METADATA
pdf_merger_advanced-2.0.0.dist-info/WHEEL
pdf_merger_advanced-2.0.0.dist-info/entry_points.txt
pdf_merger_advanced-2.0.0.dist-info/top_level.txt
pdf_merger_advanced-2.0.0.dist-info/RECORD
