Metadata-Version: 2.1
Name: pdf-merger-advanced
Version: 2.0.0
Summary: Modern PDF merger with dark mode, page ranges, and enhanced UI built with PyQt5
Home-page: https://github.com/Gunjan000/PDF-Merger-Advanced
Author: Gunjan Vaishnav
Author-email: Gunjan Vaishnav <your.email@example.com>
Maintainer-email: Gunjan Vaishnav <your.email@example.com>
License: MIT
Project-URL: Homepage, https://github.com/Gunjan000/PDF-Merger-Advanced
Project-URL: Repository, https://github.com/Gunjan000/PDF-Merger-Advanced
Project-URL: Issues, https://github.com/Gunjan000/PDF-Merger-Advanced/issues
Project-URL: Documentation, https://github.com/Gunjan000/PDF-Merger-Advanced#readme
Keywords: pdf,merger,gui,pyqt5,dark-mode,page-ranges
Classifier: Development Status :: 5 - Production/Stable
Classifier: Intended Audience :: End Users/Desktop
Classifier: License :: OSI Approved :: MIT License
Classifier: Operating System :: OS Independent
Classifier: Programming Language :: Python :: 3
Classifier: Programming Language :: Python :: 3.7
Classifier: Programming Language :: Python :: 3.8
Classifier: Programming Language :: Python :: 3.9
Classifier: Programming Language :: Python :: 3.10
Classifier: Programming Language :: Python :: 3.11
Classifier: Topic :: Office/Business
Classifier: Topic :: Utilities
Classifier: Environment :: X11 Applications :: Qt
Requires-Python: >=3.7
Requires-Dist: PyQt5 >=5.15.0
Requires-Dist: PyPDF2 >=3.0.0
Requires-Dist: pymupdf >=1.23.0
